rustsim-0.1.12.dist-info/METADATA
rustsim-0.1.12.dist-info/WHEEL
rustsim/__init__.py
rustsim/rustsim.cp310-win_amd64.pyd
rustsim-0.1.12.dist-info/RECORD
